setup.py
lib/l10n_checks.egg-info/PKG-INFO
lib/l10n_checks.egg-info/SOURCES.txt
lib/l10n_checks.egg-info/dependency_links.txt
lib/l10n_checks.egg-info/requires.txt
lib/l10n_checks.egg-info/top_level.txt
lib/mozilla/__init__.py
lib/mozilla/core/__init__.py
lib/mozilla/core/comparelocales.py
lib/mozilla/core/compatibilityPack.py
lib/mozilla/core/filter.py
lib/mozilla/core/hglayer.py
lib/mozilla/core/l10nconfigparser.py
lib/mozilla/core/logger.py
lib/mozilla/core/main.py
lib/mozilla/core/mainhelper.py
lib/mozilla/core/manifestparser.py
lib/mozilla/core/merge.py
lib/mozilla/core/statistics.py
lib/mozilla/core/testing.py
lib/mozilla/core/zip.py
lib/mozilla/format/__init__.py
lib/mozilla/format/ini/__init__.py
lib/mozilla/format/ini/parser.py
lib/mozilla/fp/__init__.py
lib/mozilla/fp/diff/__init__.py
lib/mozilla/fp/diff/mozdiff.py
lib/mozilla/io/__init__.py
lib/mozilla/io/file.py
lib/mozilla/playground/__init__.py
lib/mozilla/playground/hacks.py
scripts/check-l10n-completeness.py