Metadata-Version: 1.0
Name: l10n-checks
Version: 0.3rc
Summary: Python scripts to assist in localizing Mozilla applications and extensions
Home-page: https://wiki.mozilla.org/L10n-Checks
Author: Zbigniew Braniecki, Axel Hecht, Adrian Kalla
Author-email: akalla@aviary.pl
License: MPL 1.1/GPL 2.0/LGPL 2.1
Platform: any
Classifier: Development Status :: 4 - Beta
Classifier: Intended Audience :: Developers
Classifier: License :: OSI Approved :: GNU General Public License (GPL)
Classifier: License :: OSI Approved :: GNU Library or Lesser General Public License (LGPL)
Classifier: License :: OSI Approved :: Mozilla Public License 1.1 (MPL 1.1)
Classifier: Operating System :: OS Independent
Classifier: Programming Language :: Python
Classifier: Programming Language :: Python :: 2.5
Classifier: Programming Language :: Python :: 2.6
Classifier: Topic :: Software Development :: Libraries :: Python Modules
Classifier: Topic :: Software Development :: Localization
Classifier: Topic :: Software Development :: Testing
